mcp_oauth_dynamicclient/__init__.py
mcp_oauth_dynamicclient/__main__.py
mcp_oauth_dynamicclient/async_resource_protector.py
mcp_oauth_dynamicclient/auth_authlib.py
mcp_oauth_dynamicclient/cli.py
mcp_oauth_dynamicclient/config.py
mcp_oauth_dynamicclient/keys.py
mcp_oauth_dynamicclient/models.py
mcp_oauth_dynamicclient/py.typed
mcp_oauth_dynamicclient/redis_client.py
mcp_oauth_dynamicclient/resource_protector.py
mcp_oauth_dynamicclient/rfc7592.py
mcp_oauth_dynamicclient/routes.py
mcp_oauth_dynamicclient/server.py
mcp_oauth_dynamicclient-0.2.0.dist-info/licenses/LICENSE
mcp_oauth_dynamicclient-0.2.0.dist-info/METADATA
mcp_oauth_dynamicclient-0.2.0.dist-info/WHEEL
mcp_oauth_dynamicclient-0.2.0.dist-info/entry_points.txt
mcp_oauth_dynamicclient-0.2.0.dist-info/top_level.txt
mcp_oauth_dynamicclient-0.2.0.dist-info/RECORD
