Metadata-Version: 2.4
Name: mcp-oauth-dynamicclient
Version: 0.2.0
Summary: MCP OAuth Dynamic Client Registration Server - OAuth 2.1 and RFC 7591 compliant
Author: Andreas Trawoeger
License-Expression: Apache-2.0
Project-URL: Homepage, https://github.com/atrawog/mcp-oauth-gateway/tree/main/mcp-oauth-dynamicclient
Project-URL: Repository, https://github.com/atrawog/mcp-oauth-gateway/tree/main/mcp-oauth-dynamicclient
Project-URL: Issues, https://github.com/atrawog/mcp-oauth-gateway/issues
Project-URL: Documentation, https://atrawog.github.io/mcp-oauth-gateway
Keywords: oauth,oauth2,mcp,dynamic-client-registration,rfc7591
Classifier: Development Status :: 4 - Beta
Classifier: Intended Audience :: Developers
Classifier: Programming Language :: Python :: 3
Classifier: Programming Language :: Python :: 3.9
Classifier: Programming Language :: Python :: 3.10
Classifier: Programming Language :: Python :: 3.11
Classifier: Programming Language :: Python :: 3.12
Classifier: Topic :: Internet :: WWW/HTTP
Classifier: Topic :: Software Development :: Libraries :: Python Modules
Requires-Python: >=3.9
License-File: LICENSE
Requires-Dist: fastapi>=0.109.0
Requires-Dist: uvicorn[standard]>=0.25.0
Requires-Dist: httpx>=0.25.2
Requires-Dist: redis>=5.0.1
Requires-Dist: authlib>=1.3.0
Requires-Dist: cryptography>=41.0.7
Requires-Dist: python-multipart>=0.0.6
Requires-Dist: pydantic>=2.5.3
Requires-Dist: pydantic-settings>=2.1.0
Provides-Extra: dev
Requires-Dist: pytest>=7.0; extra == "dev"
Requires-Dist: pytest-asyncio>=0.21; extra == "dev"
Requires-Dist: pytest-cov>=4.0; extra == "dev"
Requires-Dist: black>=23.0; extra == "dev"
Requires-Dist: ruff>=0.1.0; extra == "dev"
Requires-Dist: mypy>=1.0; extra == "dev"
Dynamic: license-file
